autohelm/__init__.py
autohelm/__init__.pyc
autohelm/autohelm.py
autohelm/chart.py
autohelm/cli.py
autohelm/config.py
autohelm/course.py
autohelm/example-course.yml
autohelm/exception.py
autohelm/exception.pyc
autohelm/helm.py
autohelm/meta.py
autohelm/meta.pyc
autohelm/repository.py
tests/__init__.py
tests/test_autohelm.py
autohelm-0.7.2.dist-info/LICENSE
autohelm-0.7.2.dist-info/METADATA
autohelm-0.7.2.dist-info/WHEEL
autohelm-0.7.2.dist-info/entry_points.txt
autohelm-0.7.2.dist-info/top_level.txt
autohelm-0.7.2.dist-info/RECORD
