Metadata-Version: 2.1
Name: autohelm
Version: 0.7.2
Summary: Declarative Helm configuration with Git capability
Home-page: http://reactiveops.com/
Author: ReactiveOps, Inc.
Author-email: service@reactiveops.com
License: Apache2.0
Platform: UNKNOWN
Requires-Dist: click (==6.7)
Requires-Dist: PyYAML (==3.12)
Requires-Dist: GitPython (==2.1.3)
Requires-Dist: oyaml (>=0.4)
Requires-Dist: coloredlogs (==9.0)
Requires-Dist: semver (==2.8.0)
